Workbook

Sheet 元素单价
A1: 客户编号 | B1: 客户名称 | C1: 项次 | D1: 单个元素名称/所有元素 | E1: 网址 | F1: 网站名称 | G1: 取用规则 | H1: 升水价/手续费 | I1: 货币 | J1: 计价单位

Sheet 客户料号与宏丰料号的关系
A1: 客户料号名称 | B1: 客户产品编号 | C1: 客户图号 | D1: 宏丰料号 | E1: 付款方式 | F1: 基础货币 | G1: 报价货币 | H1: 汇率
B2: 131620 | D2: 3110100008
B3: 133824 | D3: 3121010020
B4: 73442 | D4: 3110140085
B5: 130915 | D5: 3110140119
B6: 133173 | D6: 3110780236
B7: 133174 | D7: 3110780235
B8: 133177 | D8: 3110140206
B9: 133940 | D9: 3111800003
B10: 90070 | D10: 3110100002
B11: 135430 | D11: 3120014776
B12: 90073 | D12: 3113690001
B13: 133825 | D13: 3121010380
B14: 71048 | D14: 3120016623
B15: 55246 | D15: 3111520120
B16: 66352 | D16: 3111520118
B17: 98974 | D17: 3130800001
B18: 75241 | D18: 3112550003
B19: 72813 | D19: 3120014807
B20: 53818 | D20: 3120014817
B21: 67949 | D21: 3120014816
B22: 81740 | D22: 3120014806

Sheet 物料与元素BOM
A1: 宏丰料号 | B1: 投入材质 | C1: 投入材质名称 | D1: 项次 | E1: 元素 | F1: 组成含量（%） | G1: 损耗率% | H1: 毛用量 | I1: 毛用量单位 | J1: 净用量 | K1: 净用量单位
A2: 3110100008 | C2: =VLOOKUP(VALUE(A2),物料BOM!A:D,4,0) -> AgCuONiO/Cu | D2: 1 | E2: Ag | H2: 0.0059 | I2: g/PC
A3: 3121010020 | C3: =VLOOKUP(VALUE(A3),物料BOM!A:D,4,0) -> AgNi15/Cu-Cu | D3: 1 | E3: Ag | H3: =16/1000 -> 0.016 | I3: g/PC
A4: 3110140085 | C4: =VLOOKUP(VALUE(A4),物料BOM!A:D,4,0) -> Ag/Cu | D4: 1 | E4: Ag | H4: =12.015/1000 -> 0.012015 | I4: g/PC
A5: 3110140119 | C5: =VLOOKUP(VALUE(A5),物料BOM!A:D,4,0) -> Ag/Cu | D5: 1 | E5: Ag | H5: =12.015/1000 -> 0.012015 | I5: g/PC
A6: 3110780236 | C6: =VLOOKUP(VALUE(A6),物料BOM!A:D,4,0) -> AgNi15/Cu | D6: 1 | E6: Ag | H6: 0.014 | I6: g/PC
A7: 3110780235 | C7: =VLOOKUP(VALUE(A7),物料BOM!A:D,4,0) -> AgNi15/Cu | D7: 1 | E7: Ag | H7: 0.014 | I7: g/PC
A8: 3110140206 | C8: =VLOOKUP(VALUE(A8),物料BOM!A:D,4,0) -> Ag/Cu | D8: 1 | E8: Ag | H8: 0.0165 | I8: g/PC
A9: 3110100008 | C9: =VLOOKUP(VALUE(A9),物料BOM!A:D,4,0) -> AgCuONiO/Cu | D9: 2 | E9: Cu | H9: 0.0782 | I9: g/PC
A10: 3121010020 | C10: =VLOOKUP(VALUE(A10),物料BOM!A:D,4,0) -> AgNi15/Cu-Cu | D10: 2 | E10: Cu | H10: 0.2906 | I10: g/PC
A11: 3110140085 | C11: =VLOOKUP(VALUE(A11),物料BOM!A:D,4,0) -> Ag/Cu | D11: 2 | E11: Cu | H11: =55/1000 -> 0.055 | I11: g/PC
A12: 3110140119 | C12: =VLOOKUP(VALUE(A12),物料BOM!A:D,4,0) -> Ag/Cu | D12: 2 | E12: Cu | H12: =55/1000 -> 0.055 | I12: g/PC
A13: 3110780236 | C13: =VLOOKUP(VALUE(A13),物料BOM!A:D,4,0) -> AgNi15/Cu | D13: 2 | E13: Cu | H13: 0.132 | I13: g/PC
A14: 3110780235 | C14: =VLOOKUP(VALUE(A14),物料BOM!A:D,4,0) -> AgNi15/Cu | D14: 2 | E14: Cu | H14: 0.192 | I14: g/PC
A15: 3110140206 | C15: =VLOOKUP(VALUE(A15),物料BOM!A:D,4,0) -> Ag/Cu | D15: 2 | E15: Cu | H15: 0.132 | I15: g/PC
A16: 3111800003 | C16: =VLOOKUP(VALUE(A16),物料BOM!A:D,4,0) -> C7025 | D16: 2 | E16: Cu | H16: 370 | I16: g/PC
A17: 3110140119 | C17: =VLOOKUP(VALUE(A17),物料BOM!A:D,4,0) -> Ag/Cu | D17: 2 | E17: Au | H17: =1.8/1000 -> 0.0018 | I17: g/PC
A18: 3120014776 | C18: =VLOOKUP(VALUE(A18),物料BOM!A:D,4,0) -> H85-T1 | D18: 1 | E18: Ag | H18: 1.82 | I18: g/Kg
A19: 3113690001 | C19: =VLOOKUP(VALUE(A19),物料BOM!A:D,4,0) -> AgNi(0.2)/C10500/AgNi | D19: 1 | E19: Ag | H19: 330 | I19: g/Kpcs
A20: 3121010380 | C20: =VLOOKUP(VALUE(A20),物料BOM!A:D,4,0) -> AgNi15/Cu-C7025 | D20: 1 | E20: Ag | H20: 14.5 | I20: g/Kg
A21: 3120016623 | C21: =VLOOKUP(VALUE(A21),物料BOM!A:D,4,0) -> Ag/Cu/Ni-C7025 | D21: 1 | E21: Ag | H21: 0.04 | I21: g/Kpcs
A22: 3120014776 | C22: =VLOOKUP(VALUE(A22),物料BOM!A:D,4,0) -> H85-T1 | D22: 2 | E22: Cu | H22: 586 | I22: g/Kg
A23: 3113690001 | C23: =VLOOKUP(VALUE(A23),物料BOM!A:D,4,0) -> AgNi(0.2)/C10500/AgNi | D23: 2 | E23: Cu | H23: 1040 | I23: g/Kpcs
A24: 3121010380 | C24: =VLOOKUP(VALUE(A24),物料BOM!A:D,4,0) -> AgNi15/Cu-C7025 | D24: 2 | E24: Cu | H24: 55.9 | I24: g/Kg
A25: 3120016623 | C25: =VLOOKUP(VALUE(A25),物料BOM!A:D,4,0) -> Ag/Cu/Ni-C7025 | D25: 2 | E25: Cu | H25: 0.282 | I25: g/Kpcs
A26: 3120015003 | C26: =VLOOKUP(VALUE(A26),物料BOM!A:D,4,0) -> AgNi(0.3)/Cu/Fe-SPCC-WZHF 26-07 | D26: 1 | E26: Ag | H26: 0.0265 | I26: g/pcs
A27: 3120015001 | C27: =VLOOKUP(VALUE(A27),物料BOM!A:D,4,0) -> AgNi(0.3)/Cu/Fe-SPCC-WZHF 26-35 | D27: 1 | E27: Ag | H27: 0.0265 | I27: g/pcs
A28: 3120015002 | C28: =VLOOKUP(VALUE(A28),物料BOM!A:D,4,0) -> AgNi(0.3)/Cu/Fe-SPCC-WZHF 24-21 | D28: 1 | E28: Ag | H28: 0.0265 | I28: g/pcs
A29: 3120014883 | C29: =VLOOKUP(VALUE(A29),物料BOM!A:D,4,0) -> AgNi(0.3)/Cu/Fe-SPCC-WZHF-27-80 | D29: 1 | E29: Ag | H29: 0.0265 | I29: g/pcs
... A52: 3120014816 | C52: =VLOOKUP(VALUE(A52),物料BOM!A:D,4,0) -> Ag/Cu/Ni-H | D52: 2 | E52: Cu | H52: 2.38 | I52: g/pcs
A53: 3120014806 | C53: =VLOOKUP(VALUE(A53),物料BOM!A:D,4,0) -> Ag/Ni-SPCC | D53: 2 | E53: Au | I53: g/pcs
A54: 3120014807 | C54: =VLOOKUP(VALUE(A54),物料BOM!A:D,4,0) -> Ag/Cu/Ni-H65-C | D54: 3 | E54: BeCu/SPCC | H54: 0.653 | I54: g/pcs
A55: 3120014817 | C55: =VLOOKUP(VALUE(A55),物料BOM!A:D,4,0) -> Ag/Cu/Ni-H65-C | D55: 3 | E55: BeCu/SPCC | H55: 0.653 | I55: g/pcs
A56: 3120014816 | C56: =VLOOKUP(VALUE(A56),物料BOM!A:D,4,0) -> Ag/Cu/Ni-H | D56: 3 | E56: BeCu/SPCC | I56: g/pcs
A57: 3120014806 | C57: =VLOOKUP(VALUE(A57),物料BOM!A:D,4,0) -> Ag/Ni-SPCC | D57: 3 | E57: BeCu/SPCC | H57: 0.8 | I57: g/pcs

Sheet 物料BOM
A1: 宏丰料号 | B1: 项次 | C1: 投入材质 | D1: 投入材质名称 | E1: 产出料号类型 | F1: 材料毛重 | G1: 材料净重 | H1: 重量单位 | I1: 损耗率（%） | J1: 不良率（%）
A2: 3110100008 | B2: 1 | D2: AgCuONiO/Cu | E2: AgCuONiO/Cu触点
A3: 3121010020 | B3: 1 | D3: AgNi15/Cu-Cu | E3: AgNi15/Cu-C7025可动触臂
A4: 3110140085 | B4: 1 | D4: Ag/Cu | E4: Ag/Cu触点
A5: 3110140119 | B5: 1 | D5: Ag/Cu | E5: Ag/Cu触点
A6: 3110780236 | B6: 1 | D6: AgNi15/Cu | E6: AgNi15/Cu冲件
A7: 3110780235 | B7: 1 | D7: AgNi15/Cu | E7: AgNi15/Cu冲件
A8: 3110140206 | B8: 1 | D8: Ag/Cu | E8: Ag/Cu冲件
A9: 3111800003 | B9: 1 | D9: C7025 | E9: C7025可动触臂
A10: 3110100002 | B10: 1 | D10: AgCuONiO/Cu | E10: AgCuONiO/Cu触点
A11: 3120014776 | B11: 1 | D11: H85-T1 | E11: H85-T1铆接件
A12: 3113690001 | B12: 1 | D12: AgNi(0.2)/C10500/AgNi | E12: AgNi(0.2)/C10500/AgNi(0.2)带
A13: 3121010380 | B13: 1 | D13: AgNi15/Cu-C7025 | E13: AgNi15/Cu-C7025可动触臂
... A26: 3120014883 | B26: 1 | D26: AgNi(0.3)/Cu/Fe-SPCC-WZHF-27-80 | E26: AgNi(0.3)/Cu/Fe-SPCC-WZHF-27-80焊接组件

Sheet 元素回收折扣
A1: 宏丰料号 | B1: 投入料号 | C1: 投入料号名称 | D1: 项次 | E1: 元素 | F1: 回收折扣（%）

Sheet 来料固定加工费
A1: 宏丰料号 | B1: 项次 | C1: 投入料号 | D1: 投入料号名称 | E1: 基准值 | F1: 比例（%） | G1: 货币 | H1: 计价单位 | I1: 是否随材料价格波动 | J1: 材料结算涨幅比例（%） | K1: 材料固定的涨幅值 | L1: 货币 | M1: 涨幅单位

Sheet 来料其他费用
A1: 宏丰料号 | B1: 项次 | C1: 投入料号 | D1: 投入料号名称 | E1: 项次 | F1: 要素名称 | G1: 值 | H1: 比例（%） | I1: 货币 | J1: 计价单位

Sheet 来料年降
A1: 宏丰料号 | B1: 项次 | C1: 投入料号 | D1: 投入料号名称 | E1: 年降顺序 | F1: 年降系数（%） | G1: 单次固定年降值 | H1: 货币 | I1: 计价单位 | J1: 降价次数

Sheet 来料回收折扣
A1: 宏丰料号 | B1: 项次 | C1: 投入料号 | D1: 投入料号名称 | E1: 回收折扣（%）

Sheet 自制加工费
A1: 宏丰料号 | B1: 项次 | C1: 投入料号 | D1: 投入料号名称 | E1: 项次 | F1: 工序编号 | G1: 工序名称 | H1: 值 | I1: 比例（%） | J1: 货币 | K1: 计价单位
A2: 3110100008 | B2: =COUNTIF(A$2:A2,A2) -> 1 | H2: 68.575362 | J2: RMB | K2: KPCS
A3: 3121010020 | B3: =COUNTIF(A$2:A3,A3) -> 1 | H3: 6.9002502 | J3: RMB | K3: KPCS
A4: 3121010020 | B4: =COUNTIF(A$2:A4,A4) -> 2 | H4: 30.355066 | J4: RMB | K4: KPCS
A5: 3110140085 | B5: =COUNTIF(A$2:A5,A5) -> 1 | H5: 0.49007178 | J5: RMB | K5: KPCS
A6: 3110140119 | B6: =COUNTIF(A$2:A6,A6) -> 1 | H6: 20.96538 | J6: RMB | K6: KPCS
A7: 3110780236 | B7: =COUNTIF(A$2:A7,A7) -> 1 | H7: 28.227938 | J7: RMB | K7: KPCS
A8: 3110780235 | B8: =COUNTIF(A$2:A8,A8) -> 1 | H8: 44.223802 | J8: RMB | K8: KPCS
A9: 3110140206 | B9: =COUNTIF(A$2:A9,A9) -> 1 | H9: 49.302996 | J9: RMB | K9: KPCS
A10: 3111800003 | B10: =COUNTIF(A$2:A10,A10) -> 1 | H10: 44.46162 | J10: RMB | K10: KPCS
A11: 3110110002 | B11: =COUNTIF(A$2:A11,A11) -> 1 | H11: 44.46162 | J11: RMB | K11: KPCS
A12: 3120014776 | B12: =COUNTIF(A$2:A12,A12) -> 1 | H12: 715.16759 | J12: RMB | K12: Kg
A13: 3113690001 | B13: =COUNTIF(A$2:A13,A13) -> 1 | H13: 47.82134 | J13: RMB | K13: KPCS
... A37: 3120014806 | B37: =COUNTIF(A$2:A37,A37) -> 1 | H37: 230 | J37: RMB | K37: KPCS
A38: 3110100008 | B38: =COUNTIF(A$2:A38,A38) -> 2 | G38: 焊接 | H38: 68.575362 | J38: RMB | K38: KPCS
A39: 3120015003 | B39: =COUNTIF(A$2:A39,A39) -> 5 | G39: 焊接 | H39: 0.25 | J39: RMB | K39: PC
A40: 3120015001 | B40: =COUNTIF(A$2:A40,A40) -> 5 | G40: 焊接 | H40: 0.25 | J40: RMB | K40: PC
A41: 3120014807 | B41: =COUNTIF(A$2:A41,A41) -> 2 | G41: 焊接 | H41: 0.25 | J41: RMB | K41: PC

Sheet 成品其他费用
A1: 宏丰料号 | B1: 项次 | C1: 要素名称 | D1: 值 | E1: 比例（%） | F1: 货币 | G1: 计价单位

Sheet 组成件BOM
A1: 宏丰料号 | B1: 项次 | C1: 工序编号 | D1: 组装工序 | E1: 项次 | F1: 组成件料号 | G1: 组成件名称 | H1: 组成数量 | I1: 组成单位

Sheet 组成件其他费用
A1: 宏丰料号 | B1: 项次 | C1: 工序编号 | D1: 组装工序 | E1: 项次 | F1: 组成件料号 | G1: 组成件名称 | H1: 供应商编号 | I1: 供应商名称 | J1: 项次 | K1: 要素编号 | L1: 要素名称 | M1: 值 | N1: 货币 | O1: 计价单位

Sheet 组装加工费
A1: 宏丰料号 | B1: 项次 | C1: 组装工序 | D1: 组装加工费 | E1: 货币 | F1: 计价单位 | G1: 拒收率/不良率（%）

Sheet 组装加工费年降
A1: 宏丰料号 | B1: 项次 | C1: 组装工序 | D1: 年降顺序 | E1: 年降系数（%） | F1: 单次固定年降值 | G1: 货币 | H1: 计价单位 | I1: 降价次数

Sheet 电镀方案
A1: 方案编号 | B1: 版本 | C1: 项次 | D1: 电镀元素名称 | E1: 元素单价来源网站网址 | F1: 元素单价来源网站名称 | G1: 元素单价抓取规则 | H1: 电镀面积（cm2） | I1: 镀层厚度（μm） | J1: 电镀要求

Sheet 电镀费用
A1: 宏丰料号 | B1: 电镀方案编号 | C1: 版本编号 | D1: 电镀加工费 | E1: 电镀材料费 | F1: 货币 | G1: 计价单位 | H1: 不良率（%）
A2: 3120014776 | D2: 7 | F2: RMB | G2: Kpcs

Sheet 单重
A1: 料号 | B1: 单重（g/pcs）

Sheet 年降系数
A1: 宏丰料号 | B1: 年降顺序 | C1: 年降系数（%/年） | D1: 单次固定年降金额 | E1: 货币 | F1: 计价单位 | G1: 降价次数
